repotree/__init__.py
repotree/main.py
repotree-0.1.0.dist-info/licenses/LICENSE
repotree-0.1.0.dist-info/METADATA
repotree-0.1.0.dist-info/WHEEL
repotree-0.1.0.dist-info/entry_points.txt
repotree-0.1.0.dist-info/top_level.txt
repotree-0.1.0.dist-info/RECORD
